{
  "model_artifact_id": "mod_tsmom_30_7_v1",
  "factor_id": "tsmom_30_7",
  "initial_cash": 100000.0,
  "final_cash": 96687.37,
  "final_equity": 96687.37,
  "total_net_return": -0.033126,
  "total_trades_executed": 160,
  "paper_observation_reference": "obs_mod_tsmom_30_7_v1_1780099200",
  "observation_summary": {
    "model_artifact_id": "mod_tsmom_30_7_v1",
    "reference_id": "obs_mod_tsmom_30_7_v1_1780099200",
    "observation_start": "2026-04-01T00:00:00+00:00",
    "observation_end": "2026-05-30T00:00:00+00:00",
    "duration_days": 59.0,
    "net_return": -0.0331268106095829,
    "is_complete": true,
    "meets_risk_limits": true
  },
  "period_logs": [
    {
      "decision_time": "2026-04-11T00:00:00+00:00",
      "trades_count": 10,
      "cash": 131616.79,
      "equity": 97462.93,
      "target_weights": {
        "ETHUSD": 0.15,
        "DOTUSD": -0.0556,
        "SOLUSD": -0.0556,
        "AVAXUSD": -0.0556,
        "ADAUSD": -0.0556,
        "XRPUSD": -0.0556,
        "XBTUSD": -0.0556,
        "LINKUSD": -0.0556,
        "LTCUSD": -0.0556,
        "BCHUSD": -0.0556
      },
      "open_positions": {
        "ADAUSD": -21326.701074,
        "AVAXUSD": -577.342642,
        "BCHUSD": -12.215519,
        "DOTUSD": -4154.212577,
        "ETHUSD": 6.519841,
        "LINKUSD": -596.396855,
        "LTCUSD": -98.639873,
        "SOLUSD": -63.907196,
        "XBTUSD": -0.074302,
        "XRPUSD": -3998.264926
      }
    },
    {
      "decision_time": "2026-04-18T00:00:00+00:00",
      "trades_count": 10,
      "cash": 115874.09,
      "equity": 96557.62,
      "target_weights": {
        "ETHUSD": 0.15,
        "XBTUSD": 0.15,
        "DOTUSD": -0.0625,
        "XRPUSD": -0.0625,
        "ADAUSD": -0.0625,
        "SOLUSD": -0.0625,
        "AVAXUSD": -0.0625,
        "BCHUSD": -0.0625,
        "LTCUSD": -0.0625,
        "LINKUSD": -0.0625
      },
      "open_positions": {
        "ADAUSD": -23342.59927,
        "AVAXUSD": -621.028413,
        "BCHUSD": -13.313622,
        "DOTUSD": -4525.034611,
        "ETHUSD": 5.988983,
        "LINKUSD": -627.484009,
        "LTCUSD": -107.047281,
        "SOLUSD": -68.008069,
        "XBTUSD": 0.187972,
        "XRPUSD": -4090.530712
      }
    },
    {
      "decision_time": "2026-04-25T00:00:00+00:00",
      "trades_count": 10,
      "cash": 97128.74,
      "equity": 97128.74,
      "target_weights": {
        "AVAXUSD": 0.1,
        "LINKUSD": 0.1,
        "XRPUSD": 0.1,
        "XBTUSD": 0.1,
        "ETHUSD": 0.1,
        "ADAUSD": -0.1,
        "BCHUSD": -0.1,
        "SOLUSD": -0.1,
        "DOTUSD": -0.1,
        "LTCUSD": -0.1
      },
      "open_positions": {
        "ADAUSD": -38834.826807,
        "AVAXUSD": 1034.080548,
        "BCHUSD": -21.307227,
        "DOTUSD": -7751.480981,
        "ETHUSD": 4.198877,
        "LINKUSD": 1036.28541,
        "LTCUSD": -171.920006,
        "SOLUSD": -112.791334,
        "XBTUSD": 0.125526,
        "XRPUSD": 6781.329113
      }
    },
    {
      "decision_time": "2026-05-02T00:00:00+00:00",
      "trades_count": 10,
      "cash": 63135.06,
      "equity": 97177.04,
      "target_weights": {
        "BCHUSD": 0.0556,
        "ADAUSD": 0.0556,
        "AVAXUSD": 0.0556,
        "LINKUSD": 0.0556,
        "LTCUSD": 0.0556,
        "SOLUSD": 0.0556,
        "XRPUSD": 0.0556,
        "ETHUSD": 0.0556,
        "XBTUSD": 0.0556,
        "DOTUSD": -0.15
      },
      "open_positions": {
        "ADAUSD": 21770.701055,
        "AVAXUSD": 595.097798,
        "BCHUSD": 11.994424,
        "DOTUSD": -12117.456483,
        "ETHUSD": 2.353815,
        "LINKUSD": 593.78989,
        "LTCUSD": 97.535885,
        "SOLUSD": 64.511557,
        "XBTUSD": 0.069071,
        "XRPUSD": 3899.183145
      }
    },
    {
      "decision_time": "2026-05-09T00:00:00+00:00",
      "trades_count": 10,
      "cash": 78375.3,
      "equity": 97975.64,
      "target_weights": {
        "AVAXUSD": 0.0625,
        "SOLUSD": 0.0625,
        "BCHUSD": 0.0625,
        "LTCUSD": 0.0625,
        "LINKUSD": 0.0625,
        "XRPUSD": 0.0625,
        "ETHUSD": 0.0625,
        "XBTUSD": 0.0625,
        "DOTUSD": -0.15,
        "ADAUSD": -0.15
      },
      "open_positions": {
        "ADAUSD": -53768.308591,
        "AVAXUSD": 618.073308,
        "BCHUSD": 13.596241,
        "DOTUSD": -10698.87596,
        "ETHUSD": 2.65494,
        "LINKUSD": 592.370066,
        "LTCUSD": 105.025831,
        "SOLUSD": 66.570009,
        "XBTUSD": 0.076379,
        "XRPUSD": 4318.929973
      }
    },
    {
      "decision_time": "2026-05-16T00:00:00+00:00",
      "trades_count": 10,
      "cash": 63647.15,
      "equity": 97952.84,
      "target_weights": {
        "XRPUSD": 0.0556,
        "BCHUSD": 0.0556,
        "AVAXUSD": 0.0556,
        "LTCUSD": 0.0556,
        "XBTUSD": 0.0556,
        "SOLUSD": 0.0556,
        "ADAUSD": 0.0556,
        "LINKUSD": 0.0556,
        "DOTUSD": 0.0556,
        "ETHUSD": -0.15
      },
      "open_positions": {
        "ADAUSD": 20815.547045,
        "AVAXUSD": 570.791101,
        "BCHUSD": 12.758545,
        "DOTUSD": 4137.801753,
        "ETHUSD": -6.608847,
        "LINKUSD": 540.749464,
        "LTCUSD": 94.701689,
        "SOLUSD": 61.019129,
        "XBTUSD": 0.06883,
        "XRPUSD": 3797.313185
      }
    },
    {
      "decision_time": "2026-05-23T00:00:00+00:00",
      "trades_count": 10,
      "cash": 76428.88,
      "equity": 95542.71,
      "target_weights": {
        "XRPUSD": 0.0625,
        "XBTUSD": 0.0625,
        "AVAXUSD": 0.0625,
        "SOLUSD": 0.0625,
        "DOTUSD": 0.0625,
        "LTCUSD": 0.0625,
        "ADAUSD": 0.0625,
        "LINKUSD": 0.0625,
        "BCHUSD": -0.15,
        "ETHUSD": -0.15
      },
      "open_positions": {
        "ADAUSD": 24641.382523,
        "AVAXUSD": 652.509408,
        "BCHUSD": -39.743196,
        "DOTUSD": 4748.069256,
        "ETHUSD": -6.939212,
        "LINKUSD": 634.083983,
        "LTCUSD": 113.448644,
        "SOLUSD": 70.770985,
        "XBTUSD": 0.079072,
        "XRPUSD": 4475.886942
      }
    },
    {
      "decision_time": "2026-05-30T00:00:00+00:00",
      "trades_count": 10,
      "cash": 96687.37,
      "equity": 96687.37,
      "target_weights": {
        "AVAXUSD": 0.125,
        "SOLUSD": 0.125,
        "LINKUSD": 0.125,
        "DOTUSD": 0.125,
        "BCHUSD": -0.0833,
        "ETHUSD": -0.0833,
        "LTCUSD": -0.0833,
        "XRPUSD": -0.0833,
        "ADAUSD": -0.0833,
        "XBTUSD": -0.0833
      },
      "open_positions": {
        "ADAUSD": -34627.990116,
        "AVAXUSD": 1370.486954,
        "BCHUSD": -26.678329,
        "DOTUSD": 10131.732284,
        "ETHUSD": -4.003325,
        "LINKUSD": 1340.865478,
        "LTCUSD": -155.422218,
        "SOLUSD": 147.455977,
        "XBTUSD": -0.109785,
        "XRPUSD": -6063.803683
      }
    }
  ],
  "session_run_at": "2026-07-23T15:08:33.524036+00:00"
}